BarrelShifter/Barrel_Shifter.v
// File: Barrel_Shifter.v
// Generated by MyHDL 0.11
// Date: Wed Feb 10 10:32:23 2021


`timescale 1ns/10ps

module Barrel_Shifter (
    par_in,
    par_out,
    shift_amount
);
// A barrel shifter with 3-bits shift amount for 12-bits register.
// :param par_in: Parallel input (12-bits).
// :param par_out: Parallel output (12-bits).
// :param shift_amount: Amount of shift to be executed (3-bits maximum).

input [11:0] par_in;
output [11:0] par_out;
wire [11:0] par_out;
input [2:0] shift_amount;



// Shift the input by the specified shifting amount

assign par_out = (par_in >>> shift_amount);

endmodule

BarrelShifter/Barrel_Shifter.vcd
$date
    Wed Feb 10 10:32:23 2021
$end
$version
    MyHDL 0.11
$end
$timescale
    1ns
$end

$scope module Barrel_Shifter $end
$var reg 12 ! par_out $end
$var reg 12 " par_in $end
$var reg 3 # shift_amount $end
$scope module Barrel_Shifter0 $end
$var reg 12 " par_in $end
$var reg 12 ! par_out $end
$var reg 3 # shift_amount $end
$upscope $end
$upscope $end

$enddefinitions $end
$dumpvars
b000000000000 !
b000000000000 "
b000 #
$end
b000001110101 "
b001 #
b000000111010 !
#10
b101001111100 "
b011 #
b000101001111 !
#20
b000000010000 "
b001 #
b000000001000 !
#30
b000111110111 "
b100 #
b000000011111 !
#40
b010000101100 "
b110 #
b000000010000 !
#50
b010000001011 "
b011 #
b000010000001 !
#60
b001111011011 "
b100 #
b000000111101 !
#70
b000111110100 "
b000000011111 !
#80
b100111100011 "
b000 #
b100111100011 !
#90
b110011011110 "
b110011011110 !
#100
b001111011111 "
b100 #
b000000111101 !
#110
b111000001011 "
b000 #
b111000001011 !
#120
b000101110100 "
b111 #
b000000000010 !
#130
b110111000001 "
b101 #
b000001101110 !
#140
b100110011110 "
b111 #
b000000010011 !
#150
b110000010111 "
b000 #
b110000010111 !
#160
b110010011111 "
b010 #
b001100100111 !
#170
b110011010100 "
b111 #
b000000011001 !
#180
b001011000100 "
b110 #
b000000001011 !
#190
b000101101101 "
b001 #
b000010110110 !
