BarrelShifter/Barrel_Shifter.v
// File: Barrel_Shifter.v
// Generated by MyHDL 0.11
// Date: Sun Feb  7 17:46:21 2021


`timescale 1ns/10ps

module Barrel_Shifter (
    par_in,
    par_out,
    shift_amount,
    shift,
    load
);
// A barrel shifter with 3-bits shift amount for 12-bits register.
// :param par_in: Parallel input to the register (12-bits).
// :param par_out: Parallel output of the register (12-bits).
// :param load: Load enable signal. Active High.
// :param shift: Shift enable signal. Active High.
// :param shift_amount: Amount of shift to be executed (3-bits maximum).

input [11:0] par_in;
output [11:0] par_out;
reg [11:0] par_out;
input [2:0] shift_amount;
input shift;
input load;



// Load the input into the register. or shift the output by specified amount
always @(posedge load, posedge shift) begin: BARREL_SHIFTER_LOGIC
    if ((load == 1)) begin
        par_out <= par_in;
    end
    else begin
        par_out <= (par_out >>> shift_amount);
    end
end

endmodule

BarrelShifter/Barrel_Shifter.vcd
$date
    Sun Feb  7 17:46:21 2021
$end
$version
    MyHDL 0.11
$end
$timescale
    1ns
$end

$scope module Barrel_Shifter $end
$var reg 1 ! load $end
$var reg 12 " par_in $end
$var reg 12 # par_out $end
$var reg 1 $ shift $end
$var reg 3 % shift_amount $end
$scope module Barrel_Shifter0 $end
$var reg 1 $ shift $end
$var reg 1 ! load $end
$var reg 12 " par_in $end
$var reg 12 # par_out $end
$var reg 3 % shift_amount $end
$upscope $end
$upscope $end

$enddefinitions $end
$dumpvars
0!
b000000000000 "
b000000000000 #
0$
b000 %
$end
b010010111010 "
#5
1!
b010010111010 #
#10
0!
#15
1$
b101 %
b000000100101 #
#20
0$
#25
1$
b100 %
b000000000010 #
#30
0$
#35
1$
b110 %
b000000000000 #
#40
0$
b101010001101 "
#45
1!
b101010001101 #
#50
0!
#55
1$
b101 %
b000001010100 #
#60
0$
#65
1$
b001 %
b000000101010 #
#70
0$
#75
1$
b100 %
b000000000010 #
#80
0$
#85
1$
b000 %
#90
0$
#95
1$
b110 %
b000000000000 #
#100
0$
b110101101011 "
#105
1!
b110101101011 #
#110
0!
#115
1$
b101 %
b000001101011 #
#120
0$
#125
1$
b110 %
b000000000001 #
#130
0$
#135
1$
b000000000000 #
#140
0$
b001101010101 "
#145
1!
b001101010101 #
#150
0!
#155
1$
b101 %
b000000011010 #
#160
0$
#165
1$
b000000000000 #
#170
0$
b101101011000 "
#175
1!
b101101011000 #
#180
0!
#185
1$
b001 %
b010110101100 #
#190
0$
#195
1$
b100 %
b000001011010 #
#200
0$
#205
1$
b011 %
b000000001011 #
#210
0$
#215
1$
b100 %
b000000000000 #
#220
0$
b111010011110 "
#225
1!
b111010011110 #
#230
0!
#235
1$
b101 %
b000001110100 #
#240
0$
#245
1$
b011 %
b000000001110 #
#250
0$
#255
1$
b100 %
b000000000000 #
#260
0$
b110001110001 "
#265
1!
b110001110001 #
#270
0!
#275
1$
b110 %
b000000110001 #
#280
0$
#285
1$
b101 %
b000000000001 #
#290
0$
#295
1$
b000000000000 #
#300
0$
b100110011100 "
#305
1!
b100110011100 #
#310
0!
#315
1$
b011 %
b000100110011 #
#320
0$
#325
1$
b110 %
b000000000100 #
#330
0$
#335
1$
b101 %
b000000000000 #
#340
0$
b100001111100 "
#345
1!
b100001111100 #
#350
0!
#355
1$
b000 %
#360
0$
#365
1$
b111 %
b000000010000 #
#370
0$
#375
1$
b010 %
b000000000100 #
#380
0$
#385
1$
b101 %
b000000000000 #
#390
0$
b110001101011 "
#395
1!
b110001101011 #
#400
0!
#405
1$
b000001100011 #
#410
0$
#415
1$
b110 %
b000000000001 #
#420
0$
#425
1$
b011 %
b000000000000 #
#430
0$
b000011111001 "
#435
1!
b000011111001 #
#440
0!
#445
1$
b101 %
b000000000111 #
#450
0$
#455
1$
b010 %
b000000000001 #
#460
0$
#465
1$
b100 %
b000000000000 #
#470
0$
b110001011100 "
#475
1!
b110001011100 #
#480
0!
#485
1$
b010 %
b001100010111 #
#490
0$
#495
1$
b001 %
b000110001011 #
#500
0$
#505
1$
b101 %
b000000001100 #
#510
0$
#515
1$
b100 %
b000000000000 #
#520
0$
b101101110110 "
#525
1!
b101101110110 #
#530
0!
#535
1$
b000010110111 #
#540
0$
#545
1$
b000 %
#550
0$
#555
1$
b010 %
b000000101101 #
#560
0$
#565
1$
b000000001011 #
#570
0$
#575
1$
b000 %
#580
0$
#585
1$
b101 %
b000000000000 #
#590
0$
b000101110111 "
#595
1!
b000101110111 #
#600
0!
#605
1$
b111 %
b000000000010 #
#610
0$
#615
1$
b000 %
#620
0$
#625
1$
b011 %
b000000000000 #
#630
0$
b011000000000 "
#635
1!
b011000000000 #
#640
0!
#645
1$
b010 %
b000110000000 #
#650
0$
#655
1$
b011 %
b000000110000 #
#660
0$
#665
1$
b110 %
b000000000000 #
#670
0$
b000100010010 "
#675
1!
b000100010010 #
#680
0!
#685
1$
b000000000100 #
#690
0$
#695
1$
b001 %
b000000000010 #
#700
0$
#705
1$
b010 %
b000000000000 #
#710
0$
b011101100111 "
#715
1!
b011101100111 #
#720
0!
#725
1$
b100 %
b000001110110 #
#730
0$
#735
1$
b000 %
#740
0$
#745
1$
b010 %
b000000011101 #
#750
0$
#755
1$
b110 %
b000000000000 #
#760
0$
b011100001100 "
#765
1!
b011100001100 #
#770
0!
#775
1$
b111 %
b000000001110 #
#780
0$
#785
1$
b101 %
b000000000000 #
#790
0$
b100110110000 "
#795
1!
b100110110000 #
#800
0!
#805
1$
b001 %
b010011011000 #
#810
0$
#815
1$
b100 %
b000001001101 #
#820
0$
#825
1$
b111 %
b000000000000 #
#830
0$
b110010001111 "
#835
1!
b110010001111 #
#840
0!
#845
1$
b100 %
b000011001000 #
#850
0$
#855
1$
b111 %
b000000000001 #
#860
0$
#865
1$
b000 %
#870
0$
#875
1$
b111 %
b000000000000 #
#880
0$
b010000001111 "
#885
1!
b010000001111 #
#890
0!
#895
1$
b010 %
b000100000011 #
#900
0$
#905
1$
b011 %
b000000100000 #
#910
0$
#915
1$
b100 %
b000000000010 #
#920
0$
#925
1$
b111 %
b000000000000 #
#930
0$
b101111011011 "
#935
1!
b101111011011 #
#940
0!
#945
1$
b001 %
b010111101101 #
#950
0$
#955
1$
b001011110110 #
#960
0$
#965
1$
b011 %
b000001011110 #
#970
0$
#975
1$
b000 %
#980
0$
#985
1$
b100 %
b000000000101 #
#990
0$
#995
1$
b110 %
b000000000000 #
#1000
0$
b010101010101 "
#1005
1!
b010101010101 #
#1010
0!
#1015
1$
b111 %
b000000001010 #
#1020
0$
#1025
1$
b010 %
b000000000010 #
#1030
0$
#1035
1$
b110 %
b000000000000 #
#1040
0$
b110001101011 "
#1045
1!
b110001101011 #
#1050
0!
#1055
1$
b101 %
b000001100011 #
#1060
0$
#1065
1$
b011 %
b000000001100 #
#1070
0$
#1075
1$
b110 %
b000000000000 #
#1080
0$
b100110010111 "
#1085
1!
b100110010111 #
#1090
0!
#1095
1$
b111 %
b000000010011 #
#1100
0$
#1105
1$
b000 %
#1110
0$
#1115
1$
b110 %
b000000000000 #
#1120
0$
b011000011010 "
#1125
1!
b011000011010 #
#1130
0!
#1135
1$
b001 %
b001100001101 #
#1140
0$
#1145
1$
b000110000110 #
#1150
0$
#1155
1$
b010 %
b000001100001 #
#1160
0$
#1165
1$
b011 %
b000000001100 #
#1170
0$
#1175
1$
b101 %
b000000000000 #
#1180
0$
b000110111011 "
#1185
1!
b000110111011 #
#1190
0!
#1195
1$
b111 %
b000000000011 #
#1200
0$
#1205
1$
b011 %
b000000000000 #
#1210
0$
b111011110100 "
#1215
1!
b111011110100 #
#1220
0!
#1225
1$
b110 %
b000000111011 #
#1230
0$
#1235
1$
b100 %
b000000000011 #
#1240
0$
#1245
1$
b001 %
b000000000001 #
#1250
0$
#1255
1$
b111 %
b000000000000 #
#1260
0$
b111001001011 "
#1265
1!
b111001001011 #
#1270
0!
#1275
1$
b100 %
b000011100100 #
#1280
0$
#1285
1$
b010 %
b000000111001 #
#1290
0$
#1295
1$
b101 %
b000000000001 #
#1300
0$
#1305
1$
b010 %
b000000000000 #
#1310
0$
b100011011000 "
#1315
1!
b100011011000 #
#1320
0!
#1325
1$
b111 %
b000000010001 #
#1330
0$
#1335
1$
b100 %
b000000000001 #
#1340
0$
#1345
1$
b111 %
b000000000000 #
#1350
0$
b111110101011 "
#1355
1!
b111110101011 #
#1360
0!
#1365
1$
b000000011111 #
#1370
0$
#1375
1$
b010 %
b000000000111 #
#1380
0$
#1385
1$
b000000000001 #
#1390
0$
#1395
1$
b000000000000 #
#1400
0$
b010001100111 "
#1405
1!
b010001100111 #
#1410
0!
#1415
1$
b011 %
b000010001100 #
#1420
0$
#1425
1$
b000000010001 #
#1430
0$
#1435
1$
b110 %
b000000000000 #
#1440
0$
b011000001101 "
#1445
1!
b011000001101 #
#1450
0!
#1455
1$
b001 %
b001100000110 #
#1460
0$
#1465
1$
b101 %
b000000011000 #
#1470
0$
#1475
1$
b100 %
b000000000001 #
#1480
0$
#1485
1$
b110 %
b000000000000 #
#1490
0$
b000110011110 "
#1495
1!
b000110011110 #
#1500
0!
#1505
1$
b000000000110 #
#1510
0$
#1515
1$
b111 %
b000000000000 #
#1520
0$
b111111001110 "
#1525
1!
b111111001110 #
#1530
0!
#1535
1$
b110 %
b000000111111 #
#1540
0$
#1545
1$
b010 %
b000000001111 #
#1550
0$
#1555
1$
b100 %
b000000000000 #
#1560
0$
b000010100011 "
#1565
1!
b000010100011 #
#1570
0!
#1575
1$
b000 %
#1580
0$
#1585
1$
b010 %
b000000101000 #
#1590
0$
#1595
1$
b110 %
b000000000000 #
#1600
0$
b011000000101 "
#1605
1!
b011000000101 #
#1610
0!
#1615
1$
b101 %
b000000110000 #
#1620
0$
#1625
1$
b010 %
b000000001100 #
#1630
0$
#1635
1$
b001 %
b000000000110 #
#1640
0$
#1645
1$
b010 %
b000000000001 #
#1650
0$
#1655
1$
b000 %
#1660
0$
#1665
1$
#1670
0$
#1675
1$
#1680
0$
#1685
1$
b010 %
b000000000000 #
#1690
0$
b111111000011 "
#1695
1!
b111111000011 #
#1700
0!
#1705
1$
b001 %
b011111100001 #
#1710
0$
#1715
1$
b111 %
b000000001111 #
#1720
0$
#1725
1$
b110 %
b000000000000 #
#1730
0$
b111101011010 "
#1735
1!
b111101011010 #
#1740
0!
#1745
1$
b001 %
b011110101101 #
#1750
0$
#1755
1$
b100 %
b000001111010 #
#1760
0$
#1765
1$
b101 %
b000000000011 #
#1770
0$
#1775
1$
b000 %
#1780
0$
#1785
1$
b101 %
b000000000000 #
#1790
0$
b000010010001 "
#1795
1!
b000010010001 #
#1800
0!
#1805
1$
b110 %
b000000000010 #
#1810
0$
#1815
1$
b011 %
b000000000000 #
#1820
0$
b001100011101 "
#1825
1!
b001100011101 #
#1830
0!
#1835
1$
b001 %
b000110001110 #
#1840
0$
#1845
1$
b010 %
b000001100011 #
#1850
0$
#1855
1$
b001 %
b000000110001 #
#1860
0$
#1865
1$
b000000011000 #
#1870
0$
#1875
1$
b100 %
b000000000001 #
#1880
0$
#1885
1$
b101 %
b000000000000 #
#1890
0$
b110000000111 "
#1895
1!
b110000000111 #
#1900
0!
#1905
1$
b010 %
b001100000001 #
#1910
0$
#1915
1$
b111 %
b000000000110 #
#1920
0$
#1925
1$
b011 %
b000000000000 #
#1930
0$
b111001010101 "
#1935
1!
b111001010101 #
#1940
0!
#1945
1$
b000 %
#1950
0$
#1955
1$
b110 %
b000000111001 #
#1960
0$
#1965
1$
b111 %
b000000000000 #
#1970
0$
b011101010001 "
#1975
1!
b011101010001 #
#1980
0!
#1985
1$
b000 %
#1990
0$
#1995
1$
b001 %
b001110101000 #
#2000
0$
#2005
1$
b100 %
b000000111010 #
#2010
0$
#2015
1$
b000 %
#2020
0$
#2025
1$
b001 %
b000000011101 #
#2030
0$
#2035
1$
b010 %
b000000000111 #
#2040
0$
#2045
1$
b110 %
b000000000000 #
#2050
0$
b110011000010 "
#2055
1!
b110011000010 #
#2060
0!
#2065
1$
b101 %
b000001100110 #
#2070
0$
#2075
1$
b011 %
b000000001100 #
#2080
0$
#2085
1$
b100 %
b000000000000 #
#2090
0$
b110001011111 "
#2095
1!
b110001011111 #
#2100
0!
#2105
1$
b010 %
b001100010111 #
#2110
0$
#2115
1$
b001 %
b000110001011 #
#2120
0$
#2125
1$
b111 %
b000000000011 #
#2130
0$
#2135
1$
b001 %
b000000000001 #
#2140
0$
#2145
1$
b000000000000 #
#2150
0$
b110001001100 "
#2155
1!
b110001001100 #
#2160
0!
#2165
1$
b011 %
b000110001001 #
#2170
0$
#2175
1$
b101 %
b000000001100 #
#2180
0$
#2185
1$
b000 %
#2190
0$
#2195
1$
b001 %
b000000000110 #
#2200
0$
#2205
1$
b111 %
b000000000000 #
#2210
0$
b111101001010 "
#2215
1!
b111101001010 #
#2220
0!
#2225
1$
b010 %
b001111010010 #
#2230
0$
#2235
1$
b011 %
b000001111010 #
#2240
0$
#2245
1$
b110 %
b000000000001 #
#2250
0$
#2255
1$
b101 %
b000000000000 #
#2260
0$
b011010010101 "
#2265
1!
b011010010101 #
#2270
0!
#2275
1$
b111 %
b000000001101 #
#2280
0$
#2285
1$
b010 %
b000000000011 #
#2290
0$
#2295
1$
b110 %
b000000000000 #
#2300
0$
b001100011111 "
#2305
1!
b001100011111 #
#2310
0!
#2315
1$
b111 %
b000000000110 #
#2320
0$
#2325
1$
b110 %
b000000000000 #
#2330
0$
b010001101101 "
#2335
1!
b010001101101 #
#2340
0!
#2345
1$
b100 %
b000001000110 #
#2350
0$
#2355
1$
b001 %
b000000100011 #
#2360
0$
#2365
1$
b100 %
b000000000010 #
#2370
0$
#2375
1$
b010 %
b000000000000 #
#2380
0$
b100101010001 "
#2385
1!
b100101010001 #
#2390
0!
#2395
1$
b001001010100 #
#2400
0$
#2405
1$
b111 %
b000000000100 #
#2410
0$
#2415
1$
b010 %
b000000000001 #
#2420
0$
#2425
1$
b100 %
b000000000000 #
#2430
0$
b001001010000 "
#2435
1!
b001001010000 #
#2440
0!
#2445
1$
b001 %
b000100101000 #
#2450
0$
#2455
1$
b100 %
b000000010010 #
#2460
0$
#2465
1$
b000000000001 #
#2470
0$
#2475
1$
b111 %
b000000000000 #
#2480
0$
b011011100001 "
#2485
1!
b011011100001 #
#2490
0!
#2495
1$
b100 %
b000001101110 #
#2500
0$
#2505
1$
b010 %
b000000011011 #
#2510
0$
#2515
1$
b110 %
b000000000000 #
#2520
0$
b000010111110 "
#2525
1!
b000010111110 #
#2530
0!
#2535
1$
b101 %
b000000000101 #
#2540
0$
#2545
1$
b001 %
b000000000010 #
#2550
0$
#2555
1$
b011 %
b000000000000 #
#2560
0$
b110001111010 "
#2565
1!
b110001111010 #
#2570
0!
#2575
1$
b110 %
b000000110001 #
#2580
0$
#2585
1$
b010 %
b000000001100 #
#2590
0$
#2595
1$
b111 %
b000000000000 #
#2600
0$
b010100100100 "
#2605
1!
b010100100100 #
#2610
0!
#2615
1$
b000 %
#2620
0$
#2625
1$
b111 %
b000000001010 #
#2630
0$
#2635
1$
b011 %
b000000000001 #
#2640
0$
#2645
1$
b101 %
b000000000000 #
#2650
0$
b111011100110 "
#2655
1!
b111011100110 #
#2660
0!
#2665
1$
b011 %
b000111011100 #
#2670
0$
#2675
1$
b101 %
b000000001110 #
#2680
0$
#2685
1$
b001 %
b000000000111 #
#2690
0$
#2695
1$
b000000000011 #
#2700
0$
#2705
1$
b000 %
#2710
0$
#2715
1$
b001 %
b000000000001 #
#2720
0$
#2725
1$
b010 %
b000000000000 #
#2730
0$
b110111100101 "
#2735
1!
b110111100101 #
#2740
0!
#2745
1$
b110 %
b000000110111 #
#2750
0$
#2755
1$
b000 %
#2760
0$
#2765
1$
#2770
0$
#2775
1$
b101 %
b000000000001 #
#2780
0$
#2785
1$
b110 %
b000000000000 #
#2790
0$
b100111000001 "
#2795
1!
b100111000001 #
#2800
0!
#2805
1$
b011 %
b000100111000 #
#2810
0$
#2815
1$
b111 %
b000000000010 #
#2820
0$
#2825
1$
b001 %
b000000000001 #
#2830
0$
#2835
1$
b100 %
b000000000000 #
#2840
0$
b000011011101 "
#2845
1!
b000011011101 #
#2850
0!
#2855
1$
b011 %
b000000011011 #
#2860
0$
#2865
1$
b001 %
b000000001101 #
#2870
0$
#2875
1$
b101 %
b000000000000 #
#2880
0$
b011111000010 "
#2885
1!
b011111000010 #
#2890
0!
#2895
1$
b100 %
b000001111100 #
#2900
0$
#2905
1$
b011 %
b000000001111 #
#2910
0$
#2915
1$
b101 %
b000000000000 #
#2920
0$
b000001110111 "
#2925
1!
b000001110111 #
#2930
0!
#2935
1$
b000 %
#2940
0$
#2945
1$
b010 %
b000000011101 #
#2950
0$
#2955
1$
b011 %
b000000000011 #
#2960
0$
#2965
1$
b001 %
b000000000001 #
#2970
0$
#2975
1$
b011 %
b000000000000 #
#2980
0$
b100101011111 "
#2985
1!
b100101011111 #
#2990
0!
#2995
1$
b111 %
b000000010010 #
#3000
0$
