DRegister32Bit/DRegister_32Bit.v
// File: DRegister_32Bit.v
// Generated by MyHDL 0.11
// Date: Sun Feb  7 18:09:05 2021


`timescale 1ns/10ps

module DRegister_32Bit (
    clk,
    rst,
    load,
    par_in,
    par_out
);
// Simple 32-bit data register. It can load and reset.
// :param clk: Clock signal
// :param rst: Reset signal
// :param load: Load enable signal
// :param par_in: Parallel 32-bit input
// :param par_out: Parallel 32-bit output

input clk;
input rst;
input load;
input [31:0] par_in;
output [31:0] par_out;
reg [31:0] par_out;




always @(posedge clk, negedge rst) begin: REGISTER_32BIT_LOGIC
    if (rst == 0) begin
        par_out <= 0;
    end
    else begin
        if ((rst == 0)) begin
            par_out <= 0;
        end
        else if (load) begin
            par_out <= par_in;
        end
    end
end

endmodule

DRegister32Bit/DRegister_32Bit.vcd
$date
    Sun Feb  7 18:11:35 2021
$end
$version
    MyHDL 0.11
$end
$timescale
    1ns
$end

$scope module DRegister_32Bit $end
$var reg 32 ! par_out $end
$var reg 1 " clk $end
$var reg 1 # load $end
$var reg 32 $ par_in $end
$var reg 1 % rst $end
$scope module Register0 $end
$var reg 1 " clk $end
$var reg 1 # load $end
$var reg 32 $ par_in $end
$var reg 32 ! par_out $end
$var reg 1 % rst $end
$upscope $end
$upscope $end

$enddefinitions $end
$dumpvars
b00000000000000000000000000000000 !
0"
0#
b00000000000000000000000000000000 $
0%
$end
#5
1%
1#
#10
1"
#20
0"
b11100001110011010010001000110111 $
#30
1"
b11100001110011010010001000110111 !
#40
0"
b11001001010111110111010101110111 $
#41
0#
#50
1"
#60
0"
b01010101100101110011010011010111 $
#67
1#
#70
1"
b01010101100101110011010011010111 !
#80
0"
b11100110110110011001111100110000 $
#90
1"
b11100110110110011001111100110000 !
#100
0"
b00001001011011110001100111001010 $
#110
1"
b00001001011011110001100111001010 !
#119
0#
#120
0"
b00010000001110101010110010110001 $
#130
1"
#140
0"
b10101111101001100111000000010001 $
#150
1"
1#
b10101111101001100111000000010001 !
#160
0"
b11101110000101111100001100010110 $
#170
1"
b11101110000101111100001100010110 !
#180
0"
b10100011010010011100101000001010 $
#190
1"
b10100011010010011100101000001010 !
#200
0"
b01101110000111101111011010001011 $
#204
0#
#210
1"
#220
0"
b00000000111010100000101111100111 $
#230
1"
#232
1#
#240
0"
b11100011001001111110010011000010 $
#250
1"
b11100011001001111110010011000010 !
#260
0"
b00110111001011100110011000001010 $
#270
1"
b00110111001011100110011000001010 !
#280
0"
b00001011010101000111010001111101 $
#290
1"
b00001011010101000111010001111101 !
#293
0#
#300
0"
b01101000011101101101100101101111 $
#310
1"
#316
1#
#320
0"
b11111101000010010000000100001001 $
#330
1"
b11111101000010010000000100001001 !
#340
0"
b11110110000011000101111101110111 $
#350
1"
b11110110000011000101111101110111 !
#360
0"
b10011001001110001100101011011100 $
#370
1"
b10011001001110001100101011011100 !
#374
0#
#380
0"
b11101010111011110001101101110101 $
#390
1"
#400
0"
b00110001111100111011000111011111 $
#407
1#
#410
1"
b00110001111100111011000111011111 !
#420
0"
b01101100011001111111101001000100 $
#430
1"
b01101100011001111111101001000100 !
#440
0"
b00000000010100111000101111111101 $
#450
1"
b00000000010100111000101111111101 !
#452
0#
#460
0"
b10011101010101101011101000010001 $
#470
1"
#479
0%
b00000000000000000000000000000000 !
#480
0"
b00111101000111100111110000100010 $
#482
1#
#490
1"
#500
0"
b10101010110111111111000100111101 $
#510
1"
#517
0#
#520
0"
b00111100000110010110011101001001 $
#530
1"
#540
0"
b11000110111111001110110100100111 $
#547
1#
#550
1"
#560
0"
b01110000101110011110011001100111 $
#570
1"
#580
0"
b01000001000101111000101101101010 $
#590
1"
#600
0"
b00111001101101111010000110001000 $
#610
1"
0#
#620
0"
b00101011000100100011011000111011 $
#630
1"
#637
1#
#640
0"
b01000101011110000000101100000110 $
#650
1"
#660
0"
b00111110010101111111011000010111 $
#670
1"
#680
0"
b01001001111001111000100000001000 $
#690
1"
#698
0#
#700
0"
b10010101010111001101010111001001 $
#710
1"
#720
0"
b11111010010110100100000100100001 $
#730
1"
#731
1#
#740
0"
b00000100011000111011001111010100 $
#750
1"
#760
0"
b00011000001011010001010000011111 $
#770
1"
#773
0#
#780
0"
b10011111010101001111001000101010 $
#790
1"
#792
1%
#800
0"
b11111000111000100011000111101001 $
#807
1#
#810
1"
b11111000111000100011000111101001 !
#820
0"
b11011000111100100000101111010001 $
#830
1"
b11011000111100100000101111010001 !
#840
0"
b11110111101110111101100100000111 $
#850
1"
b11110111101110111101100100000111 !
#860
0"
b10101100111111001110101111100000 $
#869
0#
#870
1"
#880
0"
b10000000001110001111110001001000 $
#890
1"
#898
1#
#900
0"
b10010001101000110000111101100000 $
#910
1"
b10010001101000110000111101100000 !
#920
0"
b01000111100101001101101100101001 $
#930
1"
b01000111100101001101101100101001 !
#935
0#
#940
0"
b00111001010011010101100110000010 $
#950
1"
#960
0"
b00000001110000010100111001001001 $
#966
1#
#970
1"
b00000001110000010100111001001001 !
#980
0"
b11110010100111111001101110011111 $
#990
1"
b11110010100111111001101110011111 !
#1000
0"
b01101110100101010011010101110010 $
#1010
1"
b01101110100101010011010101110010 !
#1020
0"
0#
b00101010110101001100001000110111 $
#1030
1"
#1040
0"
b01101100101000001111010000011001 $
#1050
1"
#1053
1#
#1060
0"
b10111101001100111000010011110011 $
#1070
1"
b10111101001100111000010011110011 !
#1080
0"
b00101011000101001000010111100111 $
#1090
1"
b00101011000101001000010111100111 !
#1091
0#
#1100
0"
b10010000010100101101110100011000 $
#1110
1"
#1115
1#
#1120
0"
b01011000110011111001011010001001 $
#1130
1"
b01011000110011111001011010001001 !
#1140
0"
b11111100000100100011010100010110 $
#1146
0#
#1150
1"
#1160
0"
b01111101100000010100010101001011 $
#1170
1"
1#
b01111101100000010100010101001011 !
#1180
0"
b01110011010010001101000010100001 $
#1190
1"
b01110011010010001101000010100001 !
#1200
0"
b00001111010010101101111101110001 $
#1210
1"
b00001111010010101101111101110001 !
#1214
0#
#1220
0"
b10110101101001001010011101100001 $
#1230
1"
#1234
1#
#1240
0"
b00001000011110011000010010011000 $
#1250
1"
b00001000011110011000010010011000 !
#1256
0%
b00000000000000000000000000000000 !
#1260
0"
b10111000011010101101010110111110 $
#1265
0#
#1270
1"
#1280
0"
b00011010011011101001111011001110 $
#1286
1#
#1290
1"
#1300
0"
b00111110001111100110011010011101 $
#1310
1"
#1320
0"
b00011100100100110101100011100111 $
#1330
1"
#1339
0#
#1340
0"
b10011101000010100110111110101111 $
#1350
1"
#1360
0"
b01001010111111000001111001001011 $
#1365
1#
#1370
1"
#1380
0"
b00101001001111101011011001101011 $
#1390
1"
#1400
0"
b10110101011001100101011101101110 $
#1402
0#
#1410
1"
#1420
0"
b10001000001010000000101001101001 $
#1430
1"
#1436
1#
#1440
0"
b01010010010110010000111010111010 $
#1450
1"
#1460
0"
b00111101001111011000001101100011 $
#1470
1"
#1480
0"
b01100011100011011111000110001111 $
#1481
0#
#1490
1"
#1500
0"
b00110011110010011010011001111011 $
#1507
1#
#1510
1"
#1515
1%
#1520
0"
b10100111111111111000111110001000 $
#1530
1"
b10100111111111111000111110001000 !
#1540
0"
b01000100110100000001001101010001 $
#1550
1"
b01000100110100000001001101010001 !
#1556
0#
#1560
0"
b11011001000110111001011010101000 $
#1570
1"
#1580
0"
b11011111001011001000001011001100 $
#1582
1#
#1590
1"
b11011111001011001000001011001100 !
#1600
0"
b00101111010100011010101000101000 $
#1610
1"
b00101111010100011010101000101000 !
#1620
0"
b01100101000001101100011001111000 $
#1624
0#
#1630
1"
#1640
0"
b10100101100111110000101100010100 $
#1644
1#
#1650
1"
b10100101100111110000101100010100 !
#1660
0"
b11110001111011001000010000111011 $
#1670
1"
b11110001111011001000010000111011 !
#1680
0"
b00011110110001011010011001010100 $
#1687
0#
#1690
1"
#1700
0"
b01101101010001111001101111000110 $
#1710
1"
1#
b01101101010001111001101111000110 !
#1720
0"
b01110101000011000100001000101101 $
#1730
1"
b01110101000011000100001000101101 !
#1740
0"
b11000100000001010100100010110100 $
#1741
0#
#1750
1"
#1760
0"
b00110101100100100010101111011010 $
#1766
1#
#1770
1"
b00110101100100100010101111011010 !
#1780
0"
b10010100000110110111001010100100 $
#1790
1"
b10010100000110110111001010100100 !
#1800
0"
b11101001101001001001011100111111 $
#1803
0#
#1810
1"
#1820
0"
b00100111110001111100100000001010 $
#1830
1"
#1835
1#
#1840
0"
b00101010000101000000100100010110 $
#1850
1"
b00101010000101000000100100010110 !
#1860
0"
b10010100110110100001101110011010 $
#1869
0#
#1870
1"
#1880
0"
b01101100111010111100101000101001 $
#1890
1"
#1891
1#
#1900
0"
b01011001101011010000101011011110 $
#1910
1"
b01011001101011010000101011011110 !
#1920
0"
b00110110101110010001010110001111 $
#1930
1"
b00110110101110010001010110001111 !
#1940
0"
b11001100110011010101001001010111 $
#1946
0#
#1950
1"
#1960
0"
b01000110101000101101011100010111 $
#1968
1#
#1970
1"
b01000110101000101101011100010111 !
#1980
0"
b10011100001110100100001100111011 $
#1990
1"
b10011100001110100100001100111011 !
#2000
0"
b00101010001000111101111110010001 $
