DRegister32Bit/DRegister_32Bit.v
// File: DRegister_32Bit.v
// Generated by MyHDL 0.11
// Date: Wed Feb 10 10:34:21 2021


`timescale 1ns/10ps

module DRegister_32Bit (
    clk,
    rst,
    load,
    par_in,
    par_out
);
// Simple 32-bit data register. It can load and reset.
// :param clk: Clock signal
// :param rst: Reset signal
// :param load: Load enable signal
// :param par_in: Parallel 32-bit input
// :param par_out: Parallel 32-bit output

input clk;
input rst;
input load;
input [31:0] par_in;
output [31:0] par_out;
reg [31:0] par_out;




always @(posedge clk, negedge rst) begin: DREGISTER_32BIT_LOGIC
    if (rst == 0) begin
        par_out <= 0;
    end
    else begin
        if (load) begin
            par_out <= par_in;
        end
    end
end

endmodule

DRegister32Bit/DRegister_32Bit.vcd
$date
    Wed Feb 10 10:34:21 2021
$end
$version
    MyHDL 0.11
$end
$timescale
    1ns
$end

$scope module DRegister_32Bit $end
$var reg 32 ! par_out $end
$var reg 1 " clk $end
$var reg 1 # load $end
$var reg 32 $ par_in $end
$var reg 1 % rst $end
$scope module Register0 $end
$var reg 1 " clk $end
$var reg 1 % rst $end
$var reg 1 # load $end
$var reg 32 $ par_in $end
$var reg 32 ! par_out $end
$upscope $end
$upscope $end

$enddefinitions $end
$dumpvars
b00000000000000000000000000000000 !
0"
0#
b00000000000000000000000000000000 $
0%
$end
#5
1%
1#
#10
1"
#20
0"
b11110000110110110111011010000000 $
#30
1"
b11110000110110110111011010000000 !
#40
0"
b10111011101011110011110110001101 $
#43
0#
#50
1"
#60
0"
b10001000110101001100011111110011 $
#70
1"
#75
1#
#80
0"
b11011110100111110100110111000011 $
#90
1"
b11011110100111110100110111000011 !
#100
0"
b00011110000011001011111111110110 $
#110
1"
b00011110000011001011111111110110 !
#111
0#
#120
0"
b00010001000011111100101011111100 $
#130
1"
#131
1#
#140
0"
b10111011100000001100100100011010 $
#150
1"
b10111011100000001100100100011010 !
#160
0"
b00100001011101101000111100001111 $
#170
1"
b00100001011101101000111100001111 !
#180
0"
b01110001111000010011000000111101 $
#187
0#
#190
1"
#200
0"
b10100101000111110100001010100000 $
#210
1"
#220
0"
1#
b11100010110010000001001101010110 $
#230
1"
b11100010110010000001001101010110 !
#240
0"
b10001010011111000101000110100110 $
#250
1"
b10001010011111000101000110100110 !
#260
0"
0#
b00111111111100000010000000111010 $
#270
1"
#280
0"
b01010100011000001001101100001101 $
#289
1#
#290
1"
b01010100011000001001101100001101 !
#300
0"
b00010011001000001011111110010011 $
#310
1"
b00010011001000001011111110010011 !
#320
0"
b01110111100000100000110100100111 $
#330
1"
b01110111100000100000110100100111 !
#334
0#
#340
0"
b01110000100011100010101101000101 $
#350
1"
#359
1#
#360
0"
b10110100110011010101010010111110 $
#370
1"
b10110100110011010101010010111110 !
#380
0"
b11100110001111100101010101101011 $
#390
1"
b11100110001111100101010101101011 !
#400
0"
b11010101010011011000000100000001 $
#410
1"
b11010101010011011000000100000001 !
#411
0#
#420
0"
b00001110101101100110110110100110 $
#430
1"
#440
0"
b00010101010101010000101101001010 $
#441
1#
#450
1"
b00010101010101010000101101001010 !
#451
0%
b00000000000000000000000000000000 !
#460
0"
b01011111011011101010110011011110 $
#470
1"
#480
0"
b01001011100101101011100010101001 $
#490
1"
#500
0"
b11010111001000010110100101000011 $
#504
0#
#510
1"
#520
0"
b10101001111111010011110101110001 $
#525
1#
#530
1"
#540
0"
b10100100001100110000011010110000 $
#550
1"
#560
0"
b10001011011010111110001010011111 $
#566
0#
#570
1"
#580
0"
b01100011100101000101101000001001 $
#587
1#
#590
1"
#600
0"
b10100100100110000100111000101011 $
#610
1"
#619
0#
#620
0"
b11111101001000100000000111001100 $
#630
1"
#640
0"
b00010110001100110110010100100111 $
#650
1"
#653
1#
#660
0"
b10001001111111110010101100001111 $
#670
1"
#680
0"
b00100101001000000110100010001010 $
#690
1"
#699
1%
#700
0"
b10100101111011001010011111010001 $
#710
1"
b10100101111011001010011111010001 !
#712
0#
#720
0"
b10100100010101010011000011001110 $
#730
1"
#739
1#
#740
0"
b10101000110111111111010100000011 $
#750
1"
b10101000110111111111010100000011 !
#760
0"
b10010110101101001010001000110111 $
#770
1"
b10010110101101001010001000110111 !
#780
0"
b01100000001100001011101101110011 $
#790
1"
b01100000001100001011101101110011 !
#795
0#
#800
0"
b00100010011111101011010011011001 $
#810
1"
#820
0"
b11101010000101100100111111101011 $
#821
1#
#830
1"
b11101010000101100100111111101011 !
#840
0"
b01100101011000010100000001001110 $
#850
1"
b01100101011000010100000001001110 !
#860
0"
b00001110000111001011010111101010 $
#870
1"
b00001110000111001011010111101010 !
#873
0#
#880
0"
b01110010111110101111010100110001 $
#890
1"
#900
0"
1#
b10111011000111111101111010100110 $
#910
1"
b10111011000111111101111010100110 !
#920
0"
b00010111100001100101011001010101 $
#930
1"
b00010111100001100101011001010101 !
#938
0#
#940
0"
b10010001010111111001001111000100 $
#950
1"
#960
0"
b10001111111000001110001010110011 $
#970
1"
#971
1#
#980
0"
b10110111000111100110000101101101 $
#990
1"
b10110111000111100110000101101101 !
#1000
0"
b01100011100101000001000011001110 $
#1010
1"
b01100011100101000001000011001110 !
#1020
0"
b00110111100010011110111110001001 $
#1025
0#
#1030
1"
#1040
0"
b01111001111011011100100011000011 $
#1050
1"
#1055
1#
#1060
0"
b10111111111110010001100100000110 $
#1070
1"
b10111111111110010001100100000110 !
#1080
0"
b01010111010110110010000011111010 $
#1090
1"
b01010111010110110010000011111010 !
#1100
0"
b01101100001110010000110000001101 $
#1110
1"
b01101100001110010000110000001101 !
#1118
0#
#1120
0"
b10110110001110010011101110011111 $
#1130
1"
#1140
0"
b10101010110010101011101110011101 $
#1147
1#
#1150
1"
b10101010110010101011101110011101 !
#1160
0"
b01010011010000100110001111010011 $
#1170
1"
b01010011010000100110001111010011 !
#1179
0%
b00000000000000000000000000000000 !
#1180
0"
b10001000010010011101010001100111 $
#1184
0#
#1190
1"
#1200
0"
b00000111100101110010000000000010 $
#1206
1#
#1210
1"
#1220
0"
b00010110100011100010000110100001 $
#1230
1"
#1240
0"
b10001110011001010110010100001010 $
#1242
0#
#1250
1"
#1260
0"
b11101011100110101011110111000100 $
#1270
1"
#1275
1#
#1280
0"
b11011000111110100010001000111000 $
#1290
1"
#1300
0"
b01000000110010010011100111101000 $
#1301
1%
#1310
1"
b01000000110010010011100111101000 !
#1320
0"
b11001100101110010111001111111010 $
#1323
0#
#1330
1"
#1340
0"
b01110110011110110110110000000100 $
#1348
1#
#1350
1"
b01110110011110110110110000000100 !
#1360
0"
b01010100110000011100110011100001 $
#1370
1"
b01010100110000011100110011100001 !
#1380
0"
b00001011110111111101110111000110 $
#1390
1"
b00001011110111111101110111000110 !
#1400
0"
b00101001000111001010111111110100 $
#1401
0#
#1410
1"
#1420
0"
b11111101110011010011110000001110 $
#1423
1#
#1430
1"
b11111101110011010011110000001110 !
#1440
0"
b01101000111110101110110101101110 $
#1450
1"
b01101000111110101110110101101110 !
#1460
0"
b11010101101111011001101110001110 $
#1470
1"
b11010101101111011001101110001110 !
#1480
0"
0#
b01011011011100001001101010011111 $
#1490
1"
#1500
0"
b00110101101010100101010011011100 $
#1501
1#
#1510
1"
b00110101101010100101010011011100 !
#1520
0"
b01100110011100001001101110001000 $
#1530
1"
b01100110011100001001101110001000 !
#1540
0"
b01010110011001111110100001001100 $
#1550
1"
b01010110011001111110100001001100 !
#1558
0#
#1560
0"
b01011001001010001010001001111110 $
#1570
1"
#1580
0"
b00011000010100000010001110110100 $
#1585
1#
#1590
1"
b00011000010100000010001110110100 !
#1600
0"
b01000011010010011100011000001111 $
#1610
1"
b01000011010010011100011000001111 !
#1620
0"
b01011010100101001000101100110001 $
#1624
0#
#1630
1"
#1640
0"
b10001000001100100100000100111100 $
#1650
1"
#1655
1#
#1660
0"
b10101000001001000000100101111001 $
#1670
1"
b10101000001001000000100101111001 !
#1680
0"
b01001000011101011010010011111110 $
#1690
1"
b01001000011101011010010011111110 !
#1700
0"
b00100100010010011010111100011010 $
#1710
1"
b00100100010010011010111100011010 !
#1717
0#
#1720
0"
b00011000001101011101001011000111 $
#1730
1"
#1740
0"
b11101000001000101010011111100101 $
#1745
1#
#1750
1"
b11101000001000101010011111100101 !
#1760
0"
b00000010001000110101111101110010 $
#1770
1"
b00000010001000110101111101110010 !
#1780
0"
b10010001111111011100011010101011 $
#1790
1"
b10010001111111011100011010101011 !
#1795
0#
#1800
0"
b00100111001100101111100100111111 $
#1810
1"
#1818
1#
#1820
0"
b11010110001111001010111101101110 $
#1830
1"
b11010110001111001010111101101110 !
#1840
0"
b10011000011110110011111011111001 $
#1850
1"
b10011000011110110011111011111001 !
#1852
0#
#1860
0"
b00100000110111011000111110110101 $
#1870
1"
#1880
0"
b11001110101010000000110101001100 $
#1885
1#
#1890
1"
b11001110101010000000110101001100 !
#1900
0"
b11011000110001110110000011011101 $
#1910
1"
b11011000110001110110000011011101 !
#1920
0"
b01111101110011110101110111010011 $
#1930
1"
b01111101110011110101110111010011 !
#1931
0#
#1940
0"
b11110101001011000100011010001000 $
#1950
1"
#1953
1#
#1960
0"
b11100001011100010010000100011001 $
#1962
0%
b00000000000000000000000000000000 !
#1970
1"
#1980
0"
b10110100001100010111100011111011 $
#1986
0#
#1990
1"
#2000
0"
b10010111011001101011000000001011 $
