SimpleMemory/Simple_Memory.v
// File: Simple_Memory.v
// Generated by MyHDL 0.11
// Date: Wed Feb 10 10:35:49 2021


`timescale 1ns/10ps

module Simple_Memory (
    clk,
    rst,
    en,
    addr,
    din,
    dout
);
// A simple memory made of 32 8-bit registers.
// :param clk: Clock signal
// :param rst: Reset signal
// :param en: Write enable signal
// :param addr: Address to write or read from
// :param din: Data input
// :param dout: Data output

input clk;
input rst;
input en;
input [4:0] addr;
input [7:0] din;
output [7:0] dout;
wire [7:0] dout;

reg [7:0] mem [0:32-1];



always @(posedge clk, negedge rst) begin: SIMPLE_MEMORY_WRITE
    if (rst == 0) begin
        mem[0] <= 0;
        mem[1] <= 0;
        mem[2] <= 0;
        mem[3] <= 0;
        mem[4] <= 0;
        mem[5] <= 0;
        mem[6] <= 0;
        mem[7] <= 0;
        mem[8] <= 0;
        mem[9] <= 0;
        mem[10] <= 0;
        mem[11] <= 0;
        mem[12] <= 0;
        mem[13] <= 0;
        mem[14] <= 0;
        mem[15] <= 0;
        mem[16] <= 0;
        mem[17] <= 0;
        mem[18] <= 0;
        mem[19] <= 0;
        mem[20] <= 0;
        mem[21] <= 0;
        mem[22] <= 0;
        mem[23] <= 0;
        mem[24] <= 0;
        mem[25] <= 0;
        mem[26] <= 0;
        mem[27] <= 0;
        mem[28] <= 0;
        mem[29] <= 0;
        mem[30] <= 0;
        mem[31] <= 0;
    end
    else begin
        if (en) begin
            mem[addr] <= din;
        end
    end
end



assign dout = mem[addr];

endmodule

SimpleMemory/Simple_Memory.vcd
$date
    Wed Feb 10 10:35:49 2021
$end
$version
    MyHDL 0.11
$end
$timescale
    1ns
$end

$scope module Simple_Memory $end
$var reg 8 ! dout $end
$var reg 5 " addr $end
$var reg 1 # clk $end
$var reg 8 $ din $end
$var reg 1 % en $end
$var reg 1 & rst $end
$scope module Memory0 $end
$var reg 1 # clk $end
$var reg 1 & rst $end
$var reg 5 " addr $end
$var reg 8 $ din $end
$var reg 8 ! dout $end
$var reg 1 % en $end
$scope module mem $end
$var reg 8 ' mem(0) $end
$var reg 8 ( mem(1) $end
$var reg 8 ) mem(2) $end
$var reg 8 * mem(3) $end
$var reg 8 + mem(4) $end
$var reg 8 , mem(5) $end
$var reg 8 - mem(6) $end
$var reg 8 . mem(7) $end
$var reg 8 / mem(8) $end
$var reg 8 0 mem(9) $end
$var reg 8 1 mem(10) $end
$var reg 8 2 mem(11) $end
$var reg 8 3 mem(12) $end
$var reg 8 4 mem(13) $end
$var reg 8 5 mem(14) $end
$var reg 8 6 mem(15) $end
$var reg 8 7 mem(16) $end
$var reg 8 8 mem(17) $end
$var reg 8 9 mem(18) $end
$var reg 8 : mem(19) $end
$var reg 8 ; mem(20) $end
$var reg 8 < mem(21) $end
$var reg 8 = mem(22) $end
$var reg 8 > mem(23) $end
$var reg 8 ? mem(24) $end
$var reg 8 @ mem(25) $end
$var reg 8 A mem(26) $end
$var reg 8 B mem(27) $end
$var reg 8 C mem(28) $end
$var reg 8 D mem(29) $end
$var reg 8 E mem(30) $end
$var reg 8 F mem(31) $end
$upscope $end
$upscope $end
$upscope $end

$enddefinitions $end
$dumpvars
b00000000 !
b00000 "
0#
b00000000 $
0%
0&
b00000000 '
b00000000 (
b00000000 )
b00000000 *
b00000000 +
b00000000 ,
b00000000 -
b00000000 .
b00000000 /
b00000000 0
b00000000 1
b00000000 2
b00000000 3
b00000000 4
b00000000 5
b00000000 6
b00000000 7
b00000000 8
b00000000 9
b00000000 :
b00000000 ;
b00000000 <
b00000000 =
b00000000 >
b00000000 ?
b00000000 @
b00000000 A
b00000000 B
b00000000 C
b00000000 D
b00000000 E
b00000000 F
$end
#5
1&
1%
#10
1#
#20
0#
b01001001 $
b10000 "
#30
1#
b01001001 7
b01001001 !
#40
0#
b01101101 $
b00100 "
b00000000 !
#50
1#
b01101101 +
b01101101 !
#58
0%
#60
0#
b10100010 $
b11110 "
b00000000 !
#70
1#
#80
0#
b11101001 $
b00111 "
#90
1#
#91
1%
#100
0#
b01110110 $
b10110 "
#110
1#
b01110110 =
b01110110 !
#120
0#
b00010111 $
b10111 "
b00000000 !
#130
1#
b00010111 >
b00010111 !
#140
0#
b01101101 $
b10010 "
b00000000 !
#143
0%
#150
1#
#160
0#
b00111010 $
b00101 "
#170
1#
#177
1%
#180
0#
b01001000 $
b10110 "
b01110110 !
#190
1#
b01001000 =
b01001000 !
#200
0#
b00101111 $
b00101 "
b00000000 !
#210
1#
b00101111 ,
b00101111 !
#220
0#
b00001001 $
b10011 "
b00000000 !
#230
1#
b00001001 :
b00001001 !
#236
0%
#240
0#
b10011101 $
b10100 "
b00000000 !
#250
1#
#260
0#
b11101101 $
b00010 "
#262
1%
#270
1#
b11101101 )
b11101101 !
#280
0#
b11100000 $
b01100 "
b00000000 !
#290
1#
b11100000 3
b11100000 !
#300
0#
b11010100 $
b00110 "
b00000000 !
#310
1#
b11010100 -
b11010100 !
#320
0#
b01100101 $
b11111 "
b00000000 !
#324
0%
#330
1#
#340
0#
b00111111 $
b10110 "
b01001000 !
#350
1#
1%
b00111111 =
b00111111 !
#360
0#
b01110000 $
b10000 "
b01001001 !
#370
1#
b01110000 7
b01110000 !
#380
0#
b00110011 $
b01110 "
b00000000 !
#390
1#
b00110011 5
b00110011 !
#393
0%
#400
0#
b00101101 $
b00000 "
b00000000 !
#410
1#
#420
0#
b00110010 $
b00111 "
#424
1%
#430
1#
b00110010 .
b00110010 !
#440
0#
b00010011 $
b01010 "
b00000000 !
#450
1#
b00010011 1
b00010011 !
#460
0#
b01000001 $
b11011 "
b00000000 !
#466
0%
#470
1#
#480
0#
b10011111 $
b00111 "
b00110010 !
#490
1#
#497
1%
#500
0#
b00000100 $
b00100 "
b01101101 !
#510
1#
b00000100 +
b00000100 !
#513
0&
b00000000 )
b00000000 +
b00000000 ,
b00000000 -
b00000000 .
b00000000 1
b00000000 3
b00000000 5
b00000000 7
b00000000 :
b00000000 =
b00000000 >
b00000000 !
#520
0#
b11000100 $
b00001 "
#530
1#
#540
0#
b11100000 $
b00101 "
#550
1#
#560
0#
b10010001 $
b01111 "
#561
0%
#570
1#
#580
0#
b00111101 $
b01110 "
#584
1%
#590
1#
#600
0#
b00001111 $
#610
1#
#620
0#
b10011101 $
#630
1#
#638
0%
#640
0#
b01001100 $
b10000 "
#650
1#
#660
0#
b11000001 $
b01001 "
#667
1%
#670
1#
#680
0#
b11011110 $
b00110 "
#690
1#
#700
0#
b11100011 $
b01100 "
#709
0%
#710
1#
#720
0#
b00110010 $
b11111 "
#725
1&
#730
1#
#731
1%
#740
0#
b00001010 $
b11001 "
#750
1#
b00001010 @
b00001010 !
#760
0#
b01111111 $
b10110 "
b00000000 !
#770
1#
b01111111 =
b01111111 !
#780
0#
b11100001 $
b01000 "
b00000000 !
#790
1#
b11100001 /
b11100001 !
#792
0%
#800
0#
b11111011 $
b11010 "
b00000000 !
#810
1#
#819
1%
#820
0#
b01000111 $
b00001 "
#830
1#
b01000111 (
b01000111 !
#840
0#
b01011101 $
b01101 "
b00000000 !
#850
1#
b01011101 4
b01011101 !
#852
0%
#860
0#
b00000000 $
b00000 "
b00000000 !
#870
1#
#880
0#
b11001010 $
b11000 "
#886
1%
#890
1#
b11001010 ?
b11001010 !
#900
0#
b00111001 $
b10001 "
b00000000 !
#910
1#
b00111001 8
b00111001 !
#920
0#
b01110010 $
b11111 "
b00000000 !
#930
1#
b01110010 F
b01110010 !
#940
0#
0%
b11101001 $
b10001 "
b00111001 !
#950
1#
#960
0#
b10010100 $
b01111 "
b00000000 !
#961
1%
#970
1#
b10010100 6
b10010100 !
#980
0#
b01100111 $
b01010 "
b00000000 !
#990
1#
b01100111 1
b01100111 !
#1000
0#
b00010001 $
b00001 "
b01000111 !
#1010
1#
b00010001 (
b00010001 !
#1013
0%
#1020
0#
b10000011 $
b01010 "
b01100111 !
#1030
1#
#1040
0#
1%
b01010011 $
b00001 "
b00010001 !
#1050
1#
b01010011 (
b01010011 !
#1060
0#
b01110000 $
b00000 "
b00000000 !
#1070
1#
b01110000 '
b01110000 !
#1080
0#
b10000110 $
b10000 "
b00000000 !
#1087
0%
#1090
1#
#1100
0#
b00110001 $
b10110 "
b01111111 !
#1110
1#
#1114
1%
#1120
0#
b01111111 $
b01000 "
b11100001 !
#1130
1#
b01111111 /
b01111111 !
#1140
0#
b10110110 $
b10010 "
b00000000 !
#1150
1#
b10110110 9
b10110110 !
#1160
0#
b00110110 $
b01101 "
b01011101 !
#1165
0%
#1170
1#
#1180
0#
b00111011 $
b10111 "
b00000000 !
#1186
1%
#1190
1#
b00111011 >
b00111011 !
#1200
0#
b10101000 $
b10011 "
b00000000 !
#1210
1#
b10101000 :
b10101000 !
#1217
0%
#1220
0#
b11010110 $
b10100 "
b00000000 !
#1230
1#
#1240
0#
1%
b00001100 $
b01001 "
#1250
1#
b00001100 0
b00001100 !
#1260
0#
b00010110 $
b00100 "
b00000000 !
#1270
1#
b00010110 +
b00010110 !
#1280
0#
b00001001 $
b10010 "
b10110110 !
#1290
1#
b00001001 9
b00001001 !
#1300
0#
b11110001 $
b10000 "
b00000000 !
#1303
0%
#1310
1#
#1320
0#
b11000011 $
b11111 "
b01110010 !
#1330
1#
#1336
1%
#1340
0#
b01010110 $
b00101 "
b00000000 !
#1350
1#
b01010110 ,
b01010110 !
#1360
0#
b11101100 $
b10010 "
b00001001 !
#1370
1#
b11101100 9
b11101100 !
#1380
0#
b10010000 $
b01000 "
b01111111 !
#1385
0%
#1390
1#
#1391
0&
b00000000 '
b00000000 (
b00000000 +
b00000000 ,
b00000000 /
b00000000 0
b00000000 1
b00000000 4
b00000000 6
b00000000 8
b00000000 9
b00000000 :
b00000000 =
b00000000 >
b00000000 ?
b00000000 @
b00000000 F
b00000000 !
#1400
0#
b01000110 $
b00010 "
#1410
1#
#1417
1%
#1420
0#
b11101001 $
b00101 "
#1430
1#
#1440
0#
b10010010 $
b01111 "
#1450
1#
#1460
0#
b00000010 $
b01100 "
#1470
1#
#1479
0%
#1480
0#
b11000100 $
b00001 "
#1490
1#
#1500
0#
b00001001 $
b11000 "
#1509
1%
#1510
1#
#1520
0#
b11101001 $
#1530
1#
#1540
0#
b00011100 $
b11111 "
#1543
0%
#1550
1#
#1560
0#
b11010010 $
b00100 "
#1568
1%
#1570
1#
#1580
0#
b10100101 $
b01100 "
#1590
1#
#1600
0#
b11001010 $
b10001 "
#1610
1#
#1620
0#
0%
b10001001 $
b10000 "
#1630
1#
#1640
0#
b01010100 $
b00101 "
#1649
1%
#1650
1#
#1660
0#
b00110001 $
b00011 "
#1670
1#
#1680
0#
b00011001 $
b01011 "
#1685
0%
#1690
1#
#1700
0#
1&
b00010001 $
b00000 "
#1710
1#
#1718
1%
#1720
0#
b11111011 $
b01001 "
#1730
1#
b11111011 0
b11111011 !
#1740
0#
b00011110 $
b00001 "
b00000000 !
#1750
1#
b00011110 (
b00011110 !
#1757
0%
#1760
0#
b10001100 $
b01101 "
b00000000 !
#1770
1#
#1780
0#
b01110111 $
b01100 "
#1790
1#
#1791
1%
#1800
0#
b00001111 $
b11101 "
#1810
1#
b00001111 D
b00001111 !
#1820
0#
b10100011 $
b11000 "
b00000000 !
#1830
1#
b10100011 ?
b10100011 !
#1835
0%
#1840
0#
b11000100 $
b10100 "
b00000000 !
#1850
1#
#1860
0#
b00011000 $
b11100 "
#1869
1%
#1870
1#
b00011000 C
b00011000 !
#1880
0#
b11011001 $
b01110 "
b00000000 !
#1890
1#
b11011001 5
b11011001 !
#1900
0#
b11101101 $
b00111 "
b00000000 !
#1910
1#
b11101101 .
b11101101 !
#1920
0#
0%
b01010000 $
b00010 "
b00000000 !
#1930
1#
#1940
0#
b01000001 $
b11010 "
#1950
1#
#1953
1%
#1960
0#
b11011100 $
b01010 "
#1970
1#
b11011100 1
b11011100 !
#1980
0#
b01001011 $
b00110 "
b00000000 !
#1990
1#
b01001011 -
b01001011 !
#1996
0%
#2000
0#
b10100010 $
b10100 "
b00000000 !
#2010
1#
#2020
0#
b00001001 $
b00100 "
#2022
1%
#2030
1#
b00001001 +
b00001001 !
#2040
0#
b00100000 $
b01100 "
b00000000 !
#2050
1#
b00100000 3
b00100000 !
#2060
0#
b01001000 $
b11111 "
b00000000 !
#2070
1#
b01001000 F
b01001000 !
#2073
0%
#2080
0#
b10111111 $
b10000 "
b00000000 !
#2090
1#
#2100
0#
b10111001 $
b01110 "
b11011001 !
#2103
1%
#2110
1#
b10111001 5
b10111001 !
#2120
0#
b10011111 $
b11111 "
b01001000 !
#2130
1#
b10011111 F
b10011111 !
#2140
0#
b10000001 $
b00000 "
b00000000 !
#2145
0%
#2150
1#
#2160
0#
b11000010 $
b10010 "
#2170
1#
#2172
1%
#2180
0#
b10100011 $
b01011 "
#2190
1#
b10100011 2
b10100011 !
#2200
0#
b10111100 $
b11010 "
b00000000 !
#2210
1#
b10111100 A
b10111100 !
#2220
0#
b10101000 $
b01101 "
b00000000 !
#2221
0%
#2230
1#
#2240
0#
b01010101 $
b11001 "
#2250
1#
#2254
1%
#2260
0#
b10100101 $
b01111 "
#2270
1#
b10100101 6
b10100101 !
#2280
0#
b00011011 $
b00110 "
b01001011 !
#2290
1#
b00011011 -
b00011011 !
#2300
0#
b00010110 $
b00000 "
b00000000 !
#2306
0%
#2310
1#
#2320
0#
b10100000 $
b10010 "
#2327
0&
b00000000 (
b00000000 +
b00000000 -
b00000000 .
b00000000 0
b00000000 1
b00000000 2
b00000000 3
b00000000 5
b00000000 6
b00000000 ?
b00000000 A
b00000000 C
b00000000 D
b00000000 F
#2330
1#
#2338
1%
#2340
0#
b11100010 $
b10111 "
#2350
1#
#2360
0#
b00001100 $
b10000 "
#2369
0%
#2370
1#
#2380
0#
b00000111 $
b00101 "
#2390
1#
1%
#2400
0#
b11110001 $
b01100 "
#2410
1#
#2420
0#
b00001001 $
b01001 "
#2427
0%
#2430
1#
#2440
0#
b01111111 $
b11010 "
#2450
1#
#2457
1%
#2460
0#
b01100000 $
b00011 "
#2470
1#
#2480
0#
b00111000 $
b10101 "
#2490
1#
#2494
0%
#2500
0#
b01010010 $
b10000 "
#2510
1#
#2520
0#
b11001010 $
b01110 "
#2523
1%
#2530
1#
#2540
0#
b00011000 $
b11100 "
#2550
1#
#2553
1&
#2555
0%
#2560
0#
b01000011 $
b00110 "
#2570
1#
#2580
0#
b01001101 $
b10101 "
#2585
1%
#2590
1#
b01001101 <
b01001101 !
#2600
0#
b00001010 $
b11001 "
b00000000 !
#2610
1#
b00001010 @
b00001010 !
#2620
0#
b10011010 $
b01110 "
b00000000 !
#2627
0%
#2630
1#
#2640
0#
b11100101 $
b01111 "
#2650
1#
#2660
0#
b01001110 $
b11110 "
#2661
1%
#2670
1#
b01001110 E
b01001110 !
#2680
0#
b11100000 $
b11001 "
b00001010 !
#2690
1#
b11100000 @
b11100000 !
#2700
0#
b10100001 $
b01101 "
b00000000 !
#2710
1#
b10100001 4
b10100001 !
#2720
0#
b11000110 $
b00101 "
b00000000 !
#2725
0%
#2730
1#
#2740
0#
b01100111 $
b00111 "
#2750
1#
#2757
1%
#2760
0#
b11100100 $
b01010 "
#2770
1#
b11100100 1
b11100100 !
#2780
0#
b00000000 $
b10001 "
b00000000 !
#2790
1#
#2800
0#
b11000010 $
#2810
1#
b11000010 8
b11000010 !
#2818
0%
#2820
0#
b00011111 $
b01111 "
b00000000 !
#2830
1#
#2840
0#
b10001110 $
b01011 "
#2847
1%
#2850
1#
b10001110 2
b10001110 !
#2860
0#
b11001101 $
b10111 "
b00000000 !
#2870
1#
b11001101 >
b11001101 !
#2880
0#
b10100101 $
b00110 "
b00000000 !
#2886
0%
#2890
1#
#2900
0#
b10010011 $
b00010 "
#2910
1#
#2915
1%
#2920
0#
b11110110 $
b00001 "
#2930
1#
b11110110 (
b11110110 !
#2940
0#
b11111000 $
b00000 "
b00000000 !
#2950
1#
b11111000 '
b11111000 !
#2955
0%
#2960
0#
b00001001 $
b10110 "
b00000000 !
#2970
1#
#2980
0#
1%
b11100010 $
b00010 "
#2990
1#
b11100010 )
b11100010 !
#3000
0#
b01101001 $
b11000 "
b00000000 !
#3010
1#
b01101001 ?
b01101001 !
#3020
0#
b10100101 $
b11001 "
b11100000 !
#3028
0%
#3030
1#
#3040
0#
b11101100 $
b01000 "
b00000000 !
#3050
1#
#3056
1%
#3060
0#
b11000011 $
b01111 "
#3070
1#
b11000011 6
b11000011 !
#3080
0#
b00001110 $
b11110 "
b01001110 !
#3090
1#
b00001110 E
b00001110 !
#3100
0#
b01001010 $
b11010 "
b00000000 !
#3110
1#
b01001010 A
b01001010 !
#3112
0%
#3120
0#
b10111011 $
b11001 "
b11100000 !
#3123
0&
b00000000 '
b00000000 (
b00000000 )
b00000000 1
b00000000 2
b00000000 4
b00000000 6
b00000000 8
b00000000 <
b00000000 >
b00000000 ?
b00000000 @
b00000000 A
b00000000 E
b00000000 !
#3130
1#
#3140
0#
1%
b11010110 $
b11010 "
#3150
1#
#3160
0#
b00111011 $
b10001 "
#3170
1#
#3180
0#
b00111111 $
b10000 "
#3190
1#
#3196
0%
#3200
0#
b00011111 $
b00101 "
#3210
1#
#3219
1%
#3220
0#
b00000101 $
b01011 "
#3230
1#
#3240
0#
b00000000 $
b00001 "
#3250
1#
#3254
0%
#3260
0#
b11011100 $
b10011 "
#3267
1&
#3270
1#
#3280
0#
b11000110 $
b00110 "
#3284
1%
#3290
1#
b11000110 -
b11000110 !
#3300
0#
b11011000 $
b00010 "
b00000000 !
#3310
1#
b11011000 )
b11011000 !
#3320
0#
b10110101 $
b01111 "
b00000000 !
#3330
1#
b10110101 6
b10110101 !
#3340
0#
b10100000 $
#3343
0%
#3350
1#
#3360
0#
b01010011 $
b00111 "
b00000000 !
#3370
1#
#3374
1%
#3380
0#
b01101101 $
b11001 "
#3390
1#
b01101101 @
b01101101 !
#3400
0#
b10010101 $
b10110 "
b00000000 !
#3410
1#
b10010101 =
b10010101 !
#3414
0%
#3420
0#
b10011101 $
b11001 "
b01101101 !
#3430
1#
#3440
0#
b10010010 $
b01010 "
b00000000 !
#3445
1%
#3450
1#
b10010010 1
b10010010 !
#3460
0#
b11110010 $
b11010 "
b00000000 !
#3470
1#
b11110010 A
b11110010 !
#3480
0#
b10011100 $
b11000 "
b00000000 !
#3490
1#
b10011100 ?
b10011100 !
#3493
0%
#3500
0#
b11110111 $
b01011 "
b00000000 !
#3510
1#
#3520
0#
b01100001 $
b10011 "
#3526
1%
#3530
1#
b01100001 :
b01100001 !
#3540
0#
b00010011 $
b01001 "
b00000000 !
#3550
1#
b00010011 0
b00010011 !
#3560
0#
b11101101 $
b00011 "
b00000000 !
#3561
0%
#3570
1#
#3580
0#
b00001000 $
b10110 "
b10010101 !
#3581
1%
#3590
1#
b00001000 =
b00001000 !
#3600
0#
b10100001 $
b11001 "
b01101101 !
#3610
1#
b10100001 @
b10100001 !
#3617
0%
#3620
0#
b11101001 $
b11010 "
b11110010 !
#3630
1#
#3640
0#
b11111010 $
b01011 "
b00000000 !
#3650
1#
1%
b11111010 2
b11111010 !
#3660
0#
b10001100 $
b00010 "
b11011000 !
#3670
1#
b10001100 )
b10001100 !
#3680
0#
b10010101 $
b00000 "
b00000000 !
#3690
1#
0%
#3700
0#
b01101001 $
b00111 "
#3710
1#
#3718
1%
#3720
0#
b01011000 $
b01110 "
#3730
1#
b01011000 5
b01011000 !
#3740
0#
b00001011 $
b01101 "
b00000000 !
#3745
0&
b00000000 )
b00000000 -
b00000000 0
b00000000 1
b00000000 2
b00000000 5
b00000000 6
b00000000 :
b00000000 =
b00000000 ?
b00000000 @
b00000000 A
#3750
1#
#3760
0#
b10100011 $
b01001 "
#3770
1#
#3777
0%
#3780
0#
b10100110 $
b00111 "
#3790
1#
#3800
0#
1%
b01000000 $
b00101 "
#3810
1#
#3820
0#
b01011000 $
b00111 "
#3830
1#
#3840
0#
b10001010 $
b00011 "
#3850
1#
#3860
0#
0%
b11111101 $
b00111 "
#3870
1#
#3873
1&
#3880
0#
b10100101 $
b00000 "
#3890
1#
#3891
1%
#3900
0#
b01010101 $
b00011 "
#3910
1#
b01010101 *
b01010101 !
#3920
0#
b01111110 $
b10101 "
b00000000 !
#3930
1#
b01111110 <
b01111110 !
#3934
0%
#3940
0#
b10000011 $
b11101 "
b00000000 !
#3950
1#
#3959
1%
#3960
0#
b11010000 $
b01111 "
#3970
1#
b11010000 6
b11010000 !
#3980
0#
b01111010 $
b01011 "
b00000000 !
#3990
1#
b01111010 2
b01111010 !
#4000
0#
b01100101 $
b11000 "
b00000000 !
